<?xml version="1.0" encoding="utf-8" ?>
<c2layout>
    <name>nivel4f45</name>
    <sid>295965586815697</sid>
    <event-sheet>Event sheet n4</event-sheet>
    <size>
        <width>1280</width>
        <height>768</height>
    </size>
    <margins>
        <horizontal>500</horizontal>
        <vertical>500</vertical>
    </margins>
    <unbounded-scrolling>0</unbounded-scrolling>
    <layers>
        <layer name="background" sid="687695178676638">
            <initially-visible>1</initially-visible>
            <background-color>255,255,255</background-color>
            <transparent>0</transparent>
            <parallax>
                <x>1</x>
                <y>1</y>
            </parallax>
            <zoom-rate>1</zoom-rate>
            <opacity>1</opacity>
            <force-own-texture>0</force-own-texture>
            <global>0</global>
            <use-render-cells>0</use-render-cells>
            <blend-mode>0</blend-mode>
            <effect-fallback>0</effect-fallback>
            <instances>
                <instance type="backgound" uid="3480">
                    <properties>
                        <initial-visibility>Visible</initial-visibility>
                        <initial-animation>Default</initial-animation>
                        <initial-frame>0</initial-frame>
                        <collisions>Enabled</collisions>
                    </properties>
                    <blend-mode>0</blend-mode>
                    <effect-fallback>0</effect-fallback>
                    <world>
                        <x>641</x>
                        <y>386</y>
                        <z>0</z>
                        <width>1280</width>
                        <height>768</height>
                        <depth>0</depth>
                        <hotspotX>0.5</hotspotX>
                        <hotspotY>0.5</hotspotY>
                        <angle>0</angle>
                        <opacity>1</opacity>
                    </world>
                </instance>
                <instance type="Pontuacao" uid="3481">
                    <properties>
                        <text>Text</text>
                        <initial-visibility>Visible</initial-visibility>
                        <font>Arial Rounded MT Bold,-37,400,0</font>
                        <color>0,0,0</color>
                        <horizontal-alignment>Right</horizontal-alignment>
                        <vertical-alignment>Center</vertical-alignment>
                        <hotspot>Top-left</hotspot>
                        <wrapping>Word</wrapping>
                        <line-height>0</line-height>
                    </properties>
                    <blend-mode>0</blend-mode>
                    <effect-fallback>0</effect-fallback>
                    <world>
                        <x>1059</x>
                        <y>25</y>
                        <z>0</z>
                        <width>176</width>
                        <height>40</height>
                        <depth>0</depth>
                        <hotspotX>0</hotspotX>
                        <hotspotY>0</hotspotY>
                        <angle>0</angle>
                        <opacity>1</opacity>
                    </world>
                </instance>
                <instance type="medalhasg" uid="3482">
                    <properties>
                        <text>Text</text>
                        <initial-visibility>Visible</initial-visibility>
                        <font>Arial Rounded MT Bold,-37,400,0</font>
                        <color>0,0,0</color>
                        <horizontal-alignment>Right</horizontal-alignment>
                        <vertical-alignment>Top</vertical-alignment>
                        <hotspot>Top-left</hotspot>
                        <wrapping>Word</wrapping>
                        <line-height>0</line-height>
                    </properties>
                    <blend-mode>0</blend-mode>
                    <effect-fallback>0</effect-fallback>
                    <world>
                        <x>576</x>
                        <y>27</y>
                        <z>0</z>
                        <width>175</width>
                        <height>44</height>
                        <depth>0</depth>
                        <hotspotX>0</hotspotX>
                        <hotspotY>0</hotspotY>
                        <angle>0</angle>
                        <opacity>1</opacity>
                    </world>
                </instance>
                <instance type="trofeis" uid="3483">
                    <properties>
                        <text>Text</text>
                        <initial-visibility>Visible</initial-visibility>
                        <font>Arial Rounded MT Bold,-37,400,0</font>
                        <color>0,0,0</color>
                        <horizontal-alignment>Right</horizontal-alignment>
                        <vertical-alignment>Top</vertical-alignment>
                        <hotspot>Top-left</hotspot>
                        <wrapping>Word</wrapping>
                        <line-height>0</line-height>
                    </properties>
                    <blend-mode>0</blend-mode>
                    <effect-fallback>0</effect-fallback>
                    <world>
                        <x>78</x>
                        <y>27</y>
                        <z>0</z>
                        <width>200</width>
                        <height>48</height>
                        <depth>0</depth>
                        <hotspotX>0</hotspotX>
                        <hotspotY>0</hotspotY>
                        <angle>0</angle>
                        <opacity>1</opacity>
                    </world>
                </instance>
                <instance type="menu" uid="3484">
                    <properties>
                        <initial-visibility>Invisible</initial-visibility>
                        <initial-animation>Default</initial-animation>
                        <initial-frame>0</initial-frame>
                        <collisions>Enabled</collisions>
                    </properties>
                    <blend-mode>0</blend-mode>
                    <effect-fallback>0</effect-fallback>
                    <world>
                        <x>90</x>
                        <y>683</y>
                        <z>0</z>
                        <width>130</width>
                        <height>130</height>
                        <depth>0</depth>
                        <hotspotX>0.5</hotspotX>
                        <hotspotY>0.5</hotspotY>
                        <angle>0</angle>
                        <opacity>1</opacity>
                    </world>
                </instance>
                <instance type="cortadan4" uid="3485">
                    <properties>
                        <initial-visibility>Visible</initial-visibility>
                        <initial-animation>Default</initial-animation>
                        <initial-frame>44</initial-frame>
                        <collisions>Enabled</collisions>
                    </properties>
                    <blend-mode>0</blend-mode>
                    <effect-fallback>0</effect-fallback>
                    <world>
                        <x>963.203613281</x>
                        <y>632.002197266</y>
                        <z>0</z>
                        <width>332.141235352</width>
                        <height>110.879997253</height>
                        <depth>0</depth>
                        <hotspotX>0.501706481</hotspotX>
                        <hotspotY>0.506493509</hotspotY>
                        <angle>0</angle>
                        <opacity>1</opacity>
                    </world>
                </instance>
                <instance type="imgfase4" uid="3486">
                    <properties>
                        <initial-visibility>Visible</initial-visibility>
                        <initial-animation>Default</initial-animation>
                        <initial-frame>44</initial-frame>
                        <collisions>Enabled</collisions>
                    </properties>
                    <behavior-instances>
                        <behavior-instance type="DragDrop">
                            <properties>
                                <axes>Both</axes>
                                <initial-state>Disabled</initial-state>
                            </properties>
                        </behavior-instance>
                    </behavior-instances>
                    <blend-mode>0</blend-mode>
                    <effect-fallback>0</effect-fallback>
                    <world>
                        <x>977</x>
                        <y>336</y>
                        <z>0</z>
                        <width>335</width>
                        <height>316</height>
                        <depth>0</depth>
                        <hotspotX>0.59375</hotspotX>
                        <hotspotY>0.453125</hotspotY>
                        <angle>0</angle>
                        <opacity>1</opacity>
                    </world>
                </instance>
                <instance type="palavrasn4" uid="3487">
                    <properties>
                        <initial-visibility>Visible</initial-visibility>
                        <initial-animation>Default</initial-animation>
                        <initial-frame>44</initial-frame>
                        <collisions>Enabled</collisions>
                    </properties>
                    <blend-mode>0</blend-mode>
                    <effect-fallback>0</effect-fallback>
                    <world>
                        <x>338.5</x>
                        <y>323.5</y>
                        <z>0</z>
                        <width>286.49041748</width>
                        <height>118.815788269</height>
                        <depth>0</depth>
                        <hotspotX>0.5</hotspotX>
                        <hotspotY>0.5</hotspotY>
                        <angle>0</angle>
                        <opacity>1</opacity>
                    </world>
                </instance>
            </instances>
            <effects />
        </layer>
        <layer name="imgmexe" sid="868425666028487">
            <initially-visible>1</initially-visible>
            <background-color>255,255,255</background-color>
            <transparent>1</transparent>
            <parallax>
                <x>1</x>
                <y>1</y>
            </parallax>
            <zoom-rate>1</zoom-rate>
            <opacity>1</opacity>
            <force-own-texture>0</force-own-texture>
            <global>0</global>
            <use-render-cells>0</use-render-cells>
            <blend-mode>0</blend-mode>
            <effect-fallback>0</effect-fallback>
            <instances>
                <instance type="silaban4" uid="3488">
                    <properties>
                        <initial-visibility>Visible</initial-visibility>
                        <initial-animation>Default</initial-animation>
                        <initial-frame>44</initial-frame>
                        <collisions>Enabled</collisions>
                    </properties>
                    <behavior-instances>
                        <behavior-instance type="DragDrop">
                            <properties>
                                <axes>Both</axes>
                                <initial-state>Enabled</initial-state>
                            </properties>
                        </behavior-instance>
                    </behavior-instances>
                    <blend-mode>0</blend-mode>
                    <effect-fallback>0</effect-fallback>
                    <world>
                        <x>335</x>
                        <y>595</y>
                        <z>0</z>
                        <width>165</width>
                        <height>97.377044678</height>
                        <depth>0</depth>
                        <hotspotX>0.504424751</hotspotX>
                        <hotspotY>0.516666651</hotspotY>
                        <angle>0</angle>
                        <opacity>1</opacity>
                    </world>
                </instance>
            </instances>
            <effects />
        </layer>
        <layer name="alert" sid="949226892069314">
            <initially-visible>1</initially-visible>
            <background-color>255,255,255</background-color>
            <transparent>1</transparent>
            <parallax>
                <x>1</x>
                <y>1</y>
            </parallax>
            <zoom-rate>1</zoom-rate>
            <opacity>1</opacity>
            <force-own-texture>0</force-own-texture>
            <global>0</global>
            <use-render-cells>0</use-render-cells>
            <blend-mode>0</blend-mode>
            <effect-fallback>0</effect-fallback>
            <instances>
                <instance type="proximafase" uid="3489">
                    <properties>
                        <initial-visibility>Invisible</initial-visibility>
                        <initial-animation>Default</initial-animation>
                        <initial-frame>0</initial-frame>
                        <collisions>Enabled</collisions>
                    </properties>
                    <blend-mode>0</blend-mode>
                    <effect-fallback>0</effect-fallback>
                    <world>
                        <x>649</x>
                        <y>518</y>
                        <z>0</z>
                        <width>997.103271484</width>
                        <height>579.092590332</height>
                        <depth>0</depth>
                        <hotspotX>0.477832526</hotspotX>
                        <hotspotY>0.674473047</hotspotY>
                        <angle>0</angle>
                        <opacity>1</opacity>
                    </world>
                </instance>
            </instances>
            <effects />
        </layer>
    </layers>
    <nonworld-instances />
    <effects />
</c2layout>
